{"data":[{"url":"BLINK_1.mp3","name":"BLINK_1"},{"url":"BLINK_2.mp3","name":"BLINK_2"},{"url":"RAW_BEAT.mp3","name":"RAW_BEAT"},{"url":"BLINK_KICK.mp3","name":"BLINK_KICK"},{"url":"BLINK_3.mp3","name":"BLINK_3"},{"url":"TAKE_ON_ME.mp3","name":"TAKE_ON_ME"},{"url":"TOM_NUGGET.mp3","name":"TOM_NUGGET"},{"url":"TOM_KICK.mp3","name":"TOM_KICK"},{"url":"TOM_SNARE.mp3","name":"TOM_SNARE"}],"name":"TAKE_ON_ME_DRUMS","type":"SOUNDSET","prefix":"http://mikehelland.com/omg/joe/cw/TAKE_ON_ME_DRUMS/","lowNote":72,"postfix":"","user_id":"1","username":"m                   ","chromatic":false,"created_at":1518800057429,"last_modified":1518800057429,"defaultSurface":"PRESET_SEQUENCER","id":840}